tzar/__init__.py
tzar/cli.py
tzar/config.py
tzar/templates.py
tzar-0.1.5.dist-info/entry_points.txt
tzar-0.1.5.dist-info/LICENSE
tzar-0.1.5.dist-info/WHEEL
tzar-0.1.5.dist-info/METADATA
tzar-0.1.5.dist-info/RECORD
