Metadata-Version: 2.1
Name: tzar
Version: 0.1.5
Summary: Manage: Tar, Zip, Anything Really!
Home-page: https://github.com/DanielVZ96/tzar
Keywords: compress,extract,tar,zip
Author: Daniel Valenzuela
Author-email: daniel@admetricks.com
Requires-Python: >=3.7,<4.0
Classifier: Programming Language :: Python :: 3
Classifier: Programming Language :: Python :: 3.7
Classifier: Programming Language :: Python :: 3.8
Classifier: Programming Language :: Python :: 3.9
Requires-Dist: click (>=8.0.1,<9.0.0)
Requires-Dist: toml (>=0.10.2,<0.11.0)
Project-URL: Repository, https://github.com/DanielVZ96/tzar
